odoo/addons/base_time_window/README.rst
odoo/addons/base_time_window/__init__.py
odoo/addons/base_time_window/__manifest__.py
odoo/addons/base_time_window/data/time_weekday.xml
odoo/addons/base_time_window/i18n/base_time_window.pot
odoo/addons/base_time_window/models/__init__.py
odoo/addons/base_time_window/models/time_weekday.py
odoo/addons/base_time_window/models/time_window_mixin.py
odoo/addons/base_time_window/readme/CONTRIBUTORS.rst
odoo/addons/base_time_window/readme/DESCRIPTION.rst
odoo/addons/base_time_window/readme/ROADMAP.rst
odoo/addons/base_time_window/readme/USAGE.rst
odoo/addons/base_time_window/security/ir.model.access.xml
odoo/addons/base_time_window/static/description/icon.png
odoo/addons/base_time_window/static/description/index.html
odoo13_addon_base_time_window-13.0.1.0.1.dist-info/METADATA
odoo13_addon_base_time_window-13.0.1.0.1.dist-info/WHEEL
odoo13_addon_base_time_window-13.0.1.0.1.dist-info/top_level.txt
odoo13_addon_base_time_window-13.0.1.0.1.dist-info/RECORD
