Metadata-Version: 2.1
Name: odoo13-addon-base-time-window
Version: 13.0.1.0.1
Summary: Base model to handle time windows
Home-page: https://github.com/OCA/server-tools
Author: ACSONE SA/NV, Camptocamp, Odoo Community Association (OCA)
Author-email: support@odoo-community.org
License: AGPL-3
Platform: UNKNOWN
Classifier: Programming Language :: Python
Classifier: Framework :: Odoo
Classifier: License :: OSI Approved :: GNU Affero General Public License v3
Requires-Python: >=3.5
Requires-Dist: odoo (<13.1dev,>=13.0a)
